LICENSE
MANIFEST.in
README.rst
setup.py
GIQLogging/__init__.py
GIQLogging.egg-info/PKG-INFO
GIQLogging.egg-info/SOURCES.txt
GIQLogging.egg-info/dependency_links.txt
GIQLogging.egg-info/requires.txt
GIQLogging.egg-info/top_level.txt