Metadata-Version: 1.1
Name: GIQLogging
Version: 1.0.4
Summary: Lightweight logstash_formatter logging initializer
Home-page: https://github.com/graphiq-data/GIQLogging
Author: Jesse Adametz - Graphiq Data Engineering
Author-email: jesse@graphiq.com
License: MIT
Keywords: logging logstash_formatter
Platform: UNKNOWN
Classifier: Development Status :: 3 - Alpha
Classifier: Intended Audience :: Developers
Classifier: Topic :: System :: Logging
Classifier: License :: OSI Approved :: MIT License
Classifier: Programming Language :: Python :: 2
Classifier: Programming Language :: Python :: 2.7
Classifier: Programming Language :: Python :: 3
